{
  "version": "7",
  "dialect": "postgresql",
  "entries": [
    {
      "idx": 0,
      "version": "7",
      "when": 1773094773680,
      "tag": "0000_strange_ultimo",
      "breakpoints": true
    },
    {
      "idx": 1,
      "version": "7",
      "when": 1773133069067,
      "tag": "0001_purple_power_man",
      "breakpoints": true
    },
    {
      "idx": 2,
      "version": "7",
      "when": 1773136070911,
      "tag": "0002_fluffy_nightshade",
      "breakpoints": true
    },
    {
      "idx": 3,
      "version": "7",
      "when": 1773221032511,
      "tag": "0003_conscious_the_enforcers",
      "breakpoints": true
    },
    {
      "idx": 4,
      "version": "7",
      "when": 1773227982688,
      "tag": "0004_glamorous_hellion",
      "breakpoints": true
    }
  ]
}